PasarGuardNodeBridge/__init__.py
PasarGuardNodeBridge/abstract_node.py
PasarGuardNodeBridge/controller.py
PasarGuardNodeBridge/grpclib.py
PasarGuardNodeBridge/rest.py
PasarGuardNodeBridge/utils.py
PasarGuardNodeBridge/common/service.proto
PasarGuardNodeBridge/common/service_grpc.py
PasarGuardNodeBridge/common/service_pb2.py
PasarGuardNodeBridge/common/service_pb2.pyi
pasarguard_node_bridge-0.4.1.dist-info/METADATA
pasarguard_node_bridge-0.4.1.dist-info/WHEEL
pasarguard_node_bridge-0.4.1.dist-info/licenses/LICENSE
pasarguard_node_bridge-0.4.1.dist-info/RECORD
