Metadata-Version: 2.4
Name: pasarguard-node-bridge
Version: 0.4.1
Summary: python package to connect your project with PasarGuard node go
Project-URL: Homepage, https://github.com/PasarGuard/node_bridge_py
Project-URL: Repository, https://github.com/PasarGuard/node_bridge_py.git
License-File: LICENSE
Keywords: PasarGuard,PasarGuard API,PasarGuard python,PasarGuard-Node,PasarGuard-panel
Classifier: Programming Language :: Python :: 3.12
Requires-Python: >=3.12
Requires-Dist: grpclib>=0.4.8
Requires-Dist: httpx>=0.28.1
Requires-Dist: protobuf>=6.31.1
